{
	"name": "CongratulateHightlight",
	"plugin-id": "Sprite",
	"sid": 374069807613040,
	"isGlobal": false,
	"editorNewInstanceIsReplica": true,
	"instanceVariables": [
		{
			"name": "StartX",
			"type": "number",
			"desc": "",
			"show": true,
			"sid": 556221058553376
		},
		{
			"name": "StartY",
			"type": "number",
			"desc": "",
			"show": true,
			"sid": 482357732280098
		}
	],
	"behaviorTypes": [
		{
			"behaviorId": "Tween",
			"name": "Tween",
			"sid": 642814105075380
		}
	],
	"effectTypes": [],
	"animations": {
		"items": [
			{
				"frames": [
					{
						"width": 209,
						"height": 76,
						"originX": 0.5,
						"originY": 0.5,
						"originalSource": "",
						"exportFormat": "lossless",
						"exportQuality": 0.8,
						"fileType": "image/png",
						"imageSpriteId": 8350686,
						"useCollisionPoly": true,
						"duration": 1,
						"tag": ""
					},
					{
						"width": 493,
						"height": 97,
						"originX": 0.5,
						"originY": 0.5,
						"originalSource": "",
						"exportFormat": "lossless",
						"exportQuality": 0.8,
						"fileType": "image/png",
						"imageSpriteId": 9822258,
						"useCollisionPoly": true,
						"duration": 1,
						"tag": ""
					},
					{
						"width": 343,
						"height": 76,
						"originX": 0.5,
						"originY": 0.5,
						"originalSource": "",
						"exportFormat": "lossless",
						"exportQuality": 0.8,
						"fileType": "image/png",
						"imageSpriteId": 6791781,
						"useCollisionPoly": true,
						"duration": 1,
						"tag": ""
					},
					{
						"width": 296,
						"height": 76,
						"originX": 0.5,
						"originY": 0.5,
						"originalSource": "",
						"exportFormat": "lossless",
						"exportQuality": 0.8,
						"fileType": "image/png",
						"imageSpriteId": 9359502,
						"useCollisionPoly": true,
						"duration": 1,
						"tag": ""
					},
					{
						"width": 410,
						"height": 96,
						"originX": 0.5,
						"originY": 0.5,
						"originalSource": "",
						"exportFormat": "lossless",
						"exportQuality": 0.8,
						"fileType": "image/png",
						"imageSpriteId": 7398947,
						"useCollisionPoly": true,
						"duration": 1,
						"tag": ""
					}
				],
				"sid": 687511889167786,
				"name": "Default",
				"isLooping": false,
				"isPingPong": false,
				"repeatCount": 1,
				"repeatTo": 0,
				"speed": 0
			}
		],
		"subfolders": []
	}
}